sinabs/_version.py
sinabs/cpp.cpython-38-darwin.so
sinabs/layers/cpp/blif_bptt.py
sinabs/layers/cpp/iaf_bptt.py
sinabs/layers/cpp/lif_bptt.py
sinabs/layers/cpp/threshold.py
sinabs_cpp-0.post0.dev14.dist-info/LICENSE
sinabs_cpp-0.post0.dev14.dist-info/METADATA
sinabs_cpp-0.post0.dev14.dist-info/WHEEL
sinabs_cpp-0.post0.dev14.dist-info/top_level.txt
sinabs_cpp-0.post0.dev14.dist-info/RECORD
